py_micro_plumberd/__init__.py
py_micro_plumberd/_version.py
py_micro_plumberd/client.py
py_micro_plumberd/command_bus.py
py_micro_plumberd/event.py
py_micro_plumberd/metadata.py
py_micro_plumberd/py.typed
py_micro_plumberd/stream.py
py_micro_plumberd-0.1.9.dist-info/licenses/LICENSE
py_micro_plumberd-0.1.9.dist-info/METADATA
py_micro_plumberd-0.1.9.dist-info/WHEEL
py_micro_plumberd-0.1.9.dist-info/top_level.txt
py_micro_plumberd-0.1.9.dist-info/RECORD
