Metadata-Version: 2.4
Name: py-micro-plumberd
Version: 0.1.9
Summary: A lightweight Python library for writing events to EventStore, compatible with .NET micro-plumberd
Author-email: ModelingEvolution <contact@modelingevolution.com>
License-Expression: MIT
Project-URL: Homepage, https://github.com/modelingevolution/py-micro-plumberd
Project-URL: Documentation, https://github.com/modelingevolution/py-micro-plumberd#readme
Project-URL: Repository, https://github.com/modelingevolution/py-micro-plumberd
Project-URL: Issues, https://github.com/modelingevolution/py-micro-plumberd/issues
Classifier: Development Status :: 3 - Alpha
Classifier: Intended Audience :: Developers
Classifier: Programming Language :: Python :: 3
Classifier: Programming Language :: Python :: 3.8
Classifier: Programming Language :: Python :: 3.9
Classifier: Programming Language :: Python :: 3.10
Classifier: Programming Language :: Python :: 3.11
Classifier: Programming Language :: Python :: 3.12
Classifier: Topic :: Software Development :: Libraries :: Python Modules
Requires-Python: >=3.8
License-File: LICENSE
Requires-Dist: esdbclient>=1.0.0
Requires-Dist: python-dateutil>=2.8.0
Requires-Dist: pydantic>=2.5.0
Provides-Extra: dev
Requires-Dist: pytest>=7.0.0; extra == "dev"
Requires-Dist: pytest-asyncio>=0.21.0; extra == "dev"
Requires-Dist: black>=23.0.0; extra == "dev"
Requires-Dist: mypy>=1.0.0; extra == "dev"
Requires-Dist: ruff>=0.1.0; extra == "dev"
Dynamic: license-file
